{
  "@context": "http://iiif.io/api/presentation/3/context.json",
  "id": "https://soduco.geohistoricaldata.org/iiif/ark:/12148/bpt6k62929887/p345-annotation.json",
  "type": "AnnotationPage",
  "items": [
    {
      "id": "https://gallica.bnf.fr/iiif/ark:/12148/bpt6k62929887/p345-tag-2000",
      "type": "Annotation",
      "motivation": "tagging",
      "body": {
        "type": "TextualBody",
        "value": "Coquel, rue Apolline, n.\u00b0 12, \u2014des Amis-de-la-Patrie.\nCornenflost, rue du faubourg Jacques, n.\u00b0 606, \u2014de l'Obser-\nvatoire.\n",
        "format": "text/plain",
        "language": "fr"
      },
      "target": {
        "type": "SpecificResource",
        "source": "https://gallica.bnf.fr/iiif/ark:/12148/bpt6k62929887/p345",
        "selector": {
          "type": "SvgSelector",
          "value": "<svg xmlns=\"http://www.w3.org/2000/svg\"><path xmlns=\"http://www.w3.org/2000/svg\" d=\"M427.05214324257116,290.48370895410574v144.65594764923054h1361.1818679144394v-144.65594764923054z\" fill=\"none\" stroke=\"#ff0000\" stroke-opacity=\"0.2\" stroke-width=\"4\"/><path xmlns=\"http://www.w3.org/2000/svg\" d=\"M427.05214324257116,290.48370895410574v59.50830255324644h139.3511256134551v-59.50830255324644z\" fill=\"none\" stroke=\"#7aecec\" stroke-opacity=\"1.0\" stroke-width=\"2\"/><path xmlns=\"http://www.w3.org/2000/svg\" d=\"M612.8536440605113,290.48370895410574v59.50830255324644h278.7022512269102v-59.50830255324644z\" fill=\"none\" stroke=\"#bfeeb7\" stroke-opacity=\"1.0\" stroke-width=\"2\"/><path xmlns=\"http://www.w3.org/2000/svg\" d=\"M1030.9070209008767,290.48370895410574v59.50830255324644h46.45037520448511v-59.50830255324644z\" fill=\"none\" stroke=\"#feca74\" stroke-opacity=\"1.0\" stroke-width=\"2\"/><path xmlns=\"http://www.w3.org/2000/svg\" d=\"M1147.0329589120893,290.48370895410574v59.50830255324644h487.72893964709283v-59.50830255324644z\" fill=\"none\" stroke=\"#bfeeb7\" stroke-opacity=\"1.0\" stroke-width=\"2\"/><path xmlns=\"http://www.w3.org/2000/svg\" d=\"M427.9895215862272,338.6404967059532v58.385919094101666h253.6049048352308v-58.385919094101666z\" fill=\"none\" stroke=\"#7aecec\" stroke-opacity=\"1.0\" stroke-width=\"2\"/><path xmlns=\"http://www.w3.org/2000/svg\" d=\"M727.7044091187727,338.6404967059532v58.385919094101666h530.264801019119v-58.385919094101666z\" fill=\"none\" stroke=\"#bfeeb7\" stroke-opacity=\"1.0\" stroke-width=\"2\"/><path xmlns=\"http://www.w3.org/2000/svg\" d=\"M1396.2991582298357,338.6404967059532v58.385919094101666h69.16497404597203v-58.385919094101666z\" fill=\"none\" stroke=\"#feca74\" stroke-opacity=\"1.0\" stroke-width=\"2\"/><path xmlns=\"http://www.w3.org/2000/svg\" d=\"M1534.62910632178,338.6404967059532v58.385919094101666h230.54991348657336v-58.385919094101666z\" fill=\"none\" stroke=\"#bfeeb7\" stroke-opacity=\"1.0\" stroke-width=\"2\"/><path xmlns=\"http://www.w3.org/2000/svg\" d=\"M478.452775528485,384.80100414156914v50.33865246176714h169.01148072864584v-50.33865246176714z\" fill=\"none\" stroke=\"#bfeeb7\" stroke-opacity=\"1.0\" stroke-width=\"2\"/></svg>"
        }
      }
    },
    {
      "id": "https://gallica.bnf.fr/iiif/ark:/12148/bpt6k62929887/p345-tag-2001",
      "type": "Annotation",
      "motivation": "tagging",
      "body": {
        "type": "TextualBody",
        "value": "Cottereau, rue du Vieux-Colombier, n.\u00b0 764,\u2014de Luxemb.\n",
        "format": "text/plain",
        "language": "fr"
      },
      "target": {
        "type": "SpecificResource",
        "source": "https://gallica.bnf.fr/iiif/ark:/12148/bpt6k62929887/p345",
        "selector": {
          "type": "SvgSelector",
          "value": "<svg xmlns=\"http://www.w3.org/2000/svg\"><path xmlns=\"http://www.w3.org/2000/svg\" d=\"M429.77289405057377,430.31872629622615v60.96409533917904h1339.920144082868v-60.96409533917904z\" fill=\"none\" stroke=\"#ff0000\" stroke-opacity=\"0.2\" stroke-width=\"4\"/><path xmlns=\"http://www.w3.org/2000/svg\" d=\"M429.77289405057377,430.31872629622615v60.96409533917904h223.32002401381135v-60.96409533917904z\" fill=\"none\" stroke=\"#7aecec\" stroke-opacity=\"1.0\" stroke-width=\"2\"/><path xmlns=\"http://www.w3.org/2000/svg\" d=\"M702.7195900674543,430.31872629622615v60.96409533917904h545.8933920337612v-60.96409533917904z\" fill=\"none\" stroke=\"#bfeeb7\" stroke-opacity=\"1.0\" stroke-width=\"2\"/><path xmlns=\"http://www.w3.org/2000/svg\" d=\"M1397.4929981104228,430.31872629622615v60.96409533917904h74.44000800460378v-60.96409533917904z\" fill=\"none\" stroke=\"#feca74\" stroke-opacity=\"1.0\" stroke-width=\"2\"/><path xmlns=\"http://www.w3.org/2000/svg\" d=\"M1521.559678118096,430.31872629622615v60.96409533917904h223.32002401381146v-60.96409533917904z\" fill=\"none\" stroke=\"#bfeeb7\" stroke-opacity=\"1.0\" stroke-width=\"2\"/></svg>"
        }
      }
    },
    {
      "id": "https://gallica.bnf.fr/iiif/ark:/12148/bpt6k62929887/p345-tag-2002",
      "type": "Annotation",
      "motivation": "tagging",
      "body": {
        "type": "TextualBody",
        "value": "Couet, cour Abbatiale, n. 1,\u2014de l'Unit\u00e9.\nCouillot, rue Denis, n.\u00b0 29, \u2014des Amis-de-la-Patrie.\n",
        "format": "text/plain",
        "language": "fr"
      },
      "target": {
        "type": "SpecificResource",
        "source": "https://gallica.bnf.fr/iiif/ark:/12148/bpt6k62929887/p345",
        "selector": {
          "type": "SvgSelector",
          "value": "<svg xmlns=\"http://www.w3.org/2000/svg\"><path xmlns=\"http://www.w3.org/2000/svg\" d=\"M430.72634751263286,479.2704351743062v103.22725808620447h1172.7880023627658v-103.22725808620447z\" fill=\"none\" stroke=\"#ff0000\" stroke-opacity=\"0.2\" stroke-width=\"4\"/><path xmlns=\"http://www.w3.org/2000/svg\" d=\"M430.72634751263286,479.2704351743062v55.93672246734303h121.99967852088483v-55.93672246734303z\" fill=\"none\" stroke=\"#7aecec\" stroke-opacity=\"1.0\" stroke-width=\"2\"/><path xmlns=\"http://www.w3.org/2000/svg\" d=\"M601.5258974418716,479.2704351743062v55.93672246734303h341.59909985847753v-55.93672246734303z\" fill=\"none\" stroke=\"#bfeeb7\" stroke-opacity=\"1.0\" stroke-width=\"2\"/><path xmlns=\"http://www.w3.org/2000/svg\" d=\"M1065.124675821234,479.2704351743062v55.93672246734303h24.399935704176983v-55.93672246734303z\" fill=\"none\" stroke=\"#feca74\" stroke-opacity=\"1.0\" stroke-width=\"2\"/><path xmlns=\"http://www.w3.org/2000/svg\" d=\"M1138.3244829337648,479.2704351743062v55.93672246734303h243.9993570417697v-55.93672246734303z\" fill=\"none\" stroke=\"#bfeeb7\" stroke-opacity=\"1.0\" stroke-width=\"2\"/><path xmlns=\"http://www.w3.org/2000/svg\" d=\"M431.64840124691307,526.673357963562v55.824335296948675h180.28706901976702v-55.824335296948675z\" fill=\"none\" stroke=\"#7aecec\" stroke-opacity=\"1.0\" stroke-width=\"2\"/><path xmlns=\"http://www.w3.org/2000/svg\" d=\"M657.0072375216218,526.673357963562v55.824335296948675h202.8229526472378v-55.824335296948675z\" fill=\"none\" stroke=\"#bfeeb7\" stroke-opacity=\"1.0\" stroke-width=\"2\"/><path xmlns=\"http://www.w3.org/2000/svg\" d=\"M995.045491933685,526.673357963562v55.824335296948675h45.07176725494185v-55.824335296948675z\" fill=\"none\" stroke=\"#feca74\" stroke-opacity=\"1.0\" stroke-width=\"2\"/><path xmlns=\"http://www.w3.org/2000/svg\" d=\"M1107.7249100710392,526.673357963562v55.824335296948675h473.2535561768884v-55.824335296948675z\" fill=\"none\" stroke=\"#bfeeb7\" stroke-opacity=\"1.0\" stroke-width=\"2\"/></svg>"
        }
      }
    },
    {
      "id": "https://gallica.bnf.fr/iiif/ark:/12148/bpt6k62929887/p345-tag-2003",
      "type": "Annotation",
      "motivation": "tagging",
      "body": {
        "type": "TextualBody",
        "value": "Coup\u00e9, rue des Boucheries, n.\u00b0 1311,\u2014des Invalides.\n",
        "format": "text/plain",
        "language": "fr"
      },
      "target": {
        "type": "SpecificResource",
        "source": "https://gallica.bnf.fr/iiif/ark:/12148/bpt6k62929887/p345",
        "selector": {
          "type": "SvgSelector",
          "value": "<svg xmlns=\"http://www.w3.org/2000/svg\"><path xmlns=\"http://www.w3.org/2000/svg\" d=\"M432.5646357304276,573.7871740162373v58.95984709262848h1234.7215219776401v-58.95984709262848z\" fill=\"none\" stroke=\"#ff0000\" stroke-opacity=\"0.2\" stroke-width=\"4\"/><path xmlns=\"http://www.w3.org/2000/svg\" d=\"M432.5646357304276,573.7871740162373v58.95984709262848h121.05112960565098v-58.95984709262848z\" fill=\"none\" stroke=\"#7aecec\" stroke-opacity=\"1.0\" stroke-width=\"2\"/><path xmlns=\"http://www.w3.org/2000/svg\" d=\"M602.036217178339,573.7871740162373v58.95984709262848h435.7840665803435v-58.95984709262848z\" fill=\"none\" stroke=\"#bfeeb7\" stroke-opacity=\"1.0\" stroke-width=\"2\"/><path xmlns=\"http://www.w3.org/2000/svg\" d=\"M1183.0816392854638,573.7871740162373v58.95984709262848h96.84090368452087v-58.95984709262848z\" fill=\"none\" stroke=\"#feca74\" stroke-opacity=\"1.0\" stroke-width=\"2\"/><path xmlns=\"http://www.w3.org/2000/svg\" d=\"M1328.342994812245,573.7871740162373v58.95984709262848h314.7329369746924v-58.95984709262848z\" fill=\"none\" stroke=\"#bfeeb7\" stroke-opacity=\"1.0\" stroke-width=\"2\"/></svg>"
        }
      }
    },
    {
      "id": "https://gallica.bnf.fr/iiif/ark:/12148/bpt6k62929887/p345-tag-2004",
      "type": "Annotation",
      "motivation": "tagging",
      "body": {
        "type": "TextualBody",
        "value": "Coupotte, ruc Georges, n.\u00b0 21,\u2014du Montblanc.\nCousin, rue de Bi\u00e8vre, n.\u00b0 14, \u2014du Panth\u00e9on.\nCoutellier, rue Lazare, n.\u00b0 43, \u2014du Montblanc.\nCraisson, rue Charenton, n.\u00b0 28,\u2014des Quinze-Vingts.\nCrespin, rue de Charenton, n.\u00b0 188, \u2014des Quinze-Vingts.\nDamas, rue de Vaugirard, n.\u00b0 1353,\u2014du Luxembourg.\n",
        "format": "text/plain",
        "language": "fr"
      },
      "target": {
        "type": "SpecificResource",
        "source": "https://gallica.bnf.fr/iiif/ark:/12148/bpt6k62929887/p345",
        "selector": {
          "type": "SvgSelector",
          "value": "<svg xmlns=\"http://www.w3.org/2000/svg\"><path xmlns=\"http://www.w3.org/2000/svg\" d=\"M433.4203327037533,617.7990917166073v289.86297680934274h1309.4469791949764v-289.86297680934274z\" fill=\"none\" stroke=\"#ff0000\" stroke-opacity=\"0.2\" stroke-width=\"4\"/><path xmlns=\"http://www.w3.org/2000/svg\" d=\"M433.4203327037533,617.7990917166073v56.51683447758364h200.58373786302673v-56.51683447758364z\" fill=\"none\" stroke=\"#7aecec\" stroke-opacity=\"1.0\" stroke-width=\"2\"/><path xmlns=\"http://www.w3.org/2000/svg\" d=\"M684.1500050325367,617.7990917166073v56.51683447758364h275.80263956166175v-56.51683447758364z\" fill=\"none\" stroke=\"#bfeeb7\" stroke-opacity=\"1.0\" stroke-width=\"2\"/><path xmlns=\"http://www.w3.org/2000/svg\" d=\"M1110.3904479914686,617.7990917166073v56.51683447758364h50.14593446575668v-56.51683447758364z\" fill=\"none\" stroke=\"#feca74\" stroke-opacity=\"1.0\" stroke-width=\"2\"/><path xmlns=\"http://www.w3.org/2000/svg\" d=\"M1210.682316922982,617.7990917166073v56.51683447758364h300.8756067945402v-56.51683447758364z\" fill=\"none\" stroke=\"#bfeeb7\" stroke-opacity=\"1.0\" stroke-width=\"2\"/><path xmlns=\"http://www.w3.org/2000/svg\" d=\"M434.39065829001794,667.7021591888387v51.05266880725628h141.96221541396474v-51.05266880725628z\" fill=\"none\" stroke=\"#7aecec\" stroke-opacity=\"1.0\" stroke-width=\"2\"/><path xmlns=\"http://www.w3.org/2000/svg\" d=\"M623.6736121753042,667.7021591888387v51.05266880725628h307.58480006359036v-51.05266880725628z\" fill=\"none\" stroke=\"#bfeeb7\" stroke-opacity=\"1.0\" stroke-width=\"2\"/><path xmlns=\"http://www.w3.org/2000/svg\" d=\"M1073.2206276528593,667.7021591888387v51.05266880725628h47.32073847132153v-51.05266880725628z\" fill=\"none\" stroke=\"#feca74\" stroke-opacity=\"1.0\" stroke-width=\"2\"/><path xmlns=\"http://www.w3.org/2000/svg\" d=\"M1191.5224738311633,667.7021591888387v51.05266880725628h260.2640615922687v-51.05266880725628z\" fill=\"none\" stroke=\"#bfeeb7\" stroke-opacity=\"1.0\" stroke-width=\"2\"/><path xmlns=\"http://www.w3.org/2000/svg\" d=\"M435.2528800512524,712.0338822404543v56.97976628939307h232.77498823894456v-56.97976628939307z\" fill=\"none\" stroke=\"#7aecec\" stroke-opacity=\"1.0\" stroke-width=\"2\"/><path xmlns=\"http://www.w3.org/2000/svg\" d=\"M714.5828659379858,712.0338822404543v56.97976628939307h232.77498823894456v-56.97976628939307z\" fill=\"none\" stroke=\"#bfeeb7\" stroke-opacity=\"1.0\" stroke-width=\"2\"/><path xmlns=\"http://www.w3.org/2000/svg\" d=\"M1087.0228471202972,712.0338822404543v56.97976628939307h46.55499764778892v-56.97976628939307z\" fill=\"none\" stroke=\"#feca74\" stroke-opacity=\"1.0\" stroke-width=\"2\"/><path xmlns=\"http://www.w3.org/2000/svg\" d=\"M1203.4103412397694,712.0338822404543v56.97976628939307h279.32998588673365v-56.97976628939307z\" fill=\"none\" stroke=\"#bfeeb7\" stroke-opacity=\"1.0\" stroke-width=\"2\"/><path xmlns=\"http://www.w3.org/2000/svg\" d=\"M436.1724322633499,759.3111280997595v54.00478980938601h189.40501331505277v-54.00478980938601z\" fill=\"none\" stroke=\"#7aecec\" stroke-opacity=\"1.0\" stroke-width=\"2\"/><path xmlns=\"http://www.w3.org/2000/svg\" d=\"M672.9286989071659,759.3111280997595v54.00478980938601h307.78314663696085v-54.00478980938601z\" fill=\"none\" stroke=\"#bfeeb7\" stroke-opacity=\"1.0\" stroke-width=\"2\"/><path xmlns=\"http://www.w3.org/2000/svg\" d=\"M1122.7656055304162,759.3111280997595v54.00478980938601h47.351253328763164v-54.00478980938601z\" fill=\"none\" stroke=\"#feca74\" stroke-opacity=\"1.0\" stroke-width=\"2\"/><path xmlns=\"http://www.w3.org/2000/svg\" d=\"M1217.4681121879426,759.3111280997595v54.00478980938601h402.48565329448695v-54.00478980938601z\" fill=\"none\" stroke=\"#bfeeb7\" stroke-opacity=\"1.0\" stroke-width=\"2\"/><path xmlns=\"http://www.w3.org/2000/svg\" d=\"M437.03704945261114,803.7578107913334v62.65446249643969h166.1965788567787v-62.65446249643969z\" fill=\"none\" stroke=\"#7aecec\" stroke-opacity=\"1.0\" stroke-width=\"2\"/><path xmlns=\"http://www.w3.org/2000/svg\" d=\"M650.7183651256123,803.7578107913334v62.65446249643969h379.87789452977984v-62.65446249643969z\" fill=\"none\" stroke=\"#bfeeb7\" stroke-opacity=\"1.0\" stroke-width=\"2\"/><path xmlns=\"http://www.w3.org/2000/svg\" d=\"M1173.0504701040597,803.7578107913334v62.65446249643969h71.22710522433374v-62.65446249643969z\" fill=\"none\" stroke=\"#feca74\" stroke-opacity=\"1.0\" stroke-width=\"2\"/><path xmlns=\"http://www.w3.org/2000/svg\" d=\"M1315.5046805527272,803.7578107913334v62.65446249643969h403.6202629378911v-62.65446249643969z\" fill=\"none\" stroke=\"#bfeeb7\" stroke-opacity=\"1.0\" stroke-width=\"2\"/><path xmlns=\"http://www.w3.org/2000/svg\" d=\"M438.01285589141014,853.9257759722495v53.73629255370054h124.64809967337315v-53.73629255370054z\" fill=\"none\" stroke=\"#7aecec\" stroke-opacity=\"1.0\" stroke-width=\"2\"/><path xmlns=\"http://www.w3.org/2000/svg\" d=\"M612.5201954341326,853.9257759722495v53.73629255370054h398.87391895479414v-53.73629255370054z\" fill=\"none\" stroke=\"#bfeeb7\" stroke-opacity=\"1.0\" stroke-width=\"2\"/><path xmlns=\"http://www.w3.org/2000/svg\" d=\"M1160.9718339969745,853.9257759722495v53.73629255370054h99.71847973869853v-53.73629255370054z\" fill=\"none\" stroke=\"#feca74\" stroke-opacity=\"1.0\" stroke-width=\"2\"/><path xmlns=\"http://www.w3.org/2000/svg\" d=\"M1310.549553605022,853.9257759722495v53.73629255370054h324.0850591507701v-53.73629255370054z\" fill=\"none\" stroke=\"#bfeeb7\" stroke-opacity=\"1.0\" stroke-width=\"2\"/></svg>"
        }
      }
    },
    {
      "id": "https://gallica.bnf.fr/iiif/ark:/12148/bpt6k62929887/p345-tag-2005",
      "type": "Annotation",
      "motivation": "tagging",
      "body": {
        "type": "TextualBody",
        "value": "Damour, rue des Vieux-Augustins, n.\u00b0 24,\u2014du Mail.\n",
        "format": "text/plain",
        "language": "fr"
      },
      "target": {
        "type": "SpecificResource",
        "source": "https://gallica.bnf.fr/iiif/ark:/12148/bpt6k62929887/p345",
        "selector": {
          "type": "SvgSelector",
          "value": "<svg xmlns=\"http://www.w3.org/2000/svg\"><path xmlns=\"http://www.w3.org/2000/svg\" d=\"M438.93162536493907,901.1684732940612v56.83520443173063h1198.2744773917293v-56.83520443173063z\" fill=\"none\" stroke=\"#ff0000\" stroke-opacity=\"0.2\" stroke-width=\"4\"/><path xmlns=\"http://www.w3.org/2000/svg\" d=\"M438.93162536493907,901.1684732940612v56.83520443173063h146.72748702755868v-56.83520443173063z\" fill=\"none\" stroke=\"#7aecec\" stroke-opacity=\"1.0\" stroke-width=\"2\"/><path xmlns=\"http://www.w3.org/2000/svg\" d=\"M634.5682747350173,901.1684732940612v56.83520443173063h562.4553669389751v-56.83520443173063z\" fill=\"none\" stroke=\"#bfeeb7\" stroke-opacity=\"1.0\" stroke-width=\"2\"/><path xmlns=\"http://www.w3.org/2000/svg\" d=\"M1343.751128701551,901.1684732940612v56.83520443173063h48.90916234251961v-56.83520443173063z\" fill=\"none\" stroke=\"#feca74\" stroke-opacity=\"1.0\" stroke-width=\"2\"/><path xmlns=\"http://www.w3.org/2000/svg\" d=\"M1441.56945338659,901.1684732940612v56.83520443173063h171.18206819881834v-56.83520443173063z\" fill=\"none\" stroke=\"#bfeeb7\" stroke-opacity=\"1.0\" stroke-width=\"2\"/></svg>"
        }
      }
    },
    {
      "id": "https://gallica.bnf.fr/iiif/ark:/12148/bpt6k62929887/p345-tag-2006",
      "type": "Annotation",
      "motivation": "tagging",
      "body": {
        "type": "TextualBody",
        "value": "Dauprat, rue Regrati\u00e8re, n. 22, \u2014de la Fraternit\u00e9.\n",
        "format": "text/plain",
        "language": "fr"
      },
      "target": {
        "type": "SpecificResource",
        "source": "https://gallica.bnf.fr/iiif/ark:/12148/bpt6k62929887/p345",
        "selector": {
          "type": "SvgSelector",
          "value": "<svg xmlns=\"http://www.w3.org/2000/svg\"><path xmlns=\"http://www.w3.org/2000/svg\" d=\"M439.85207275170814,948.4902017911274v53.803793867429135h1150.6689945246376v-53.803793867429135z\" fill=\"none\" stroke=\"#ff0000\" stroke-opacity=\"0.2\" stroke-width=\"4\"/><path xmlns=\"http://www.w3.org/2000/svg\" d=\"M439.85207275170814,948.4902017911274v53.803793867429135h92.05351956197102v-53.803793867429135z\" fill=\"none\" stroke=\"#7aecec\" stroke-opacity=\"1.0\" stroke-width=\"2\"/><path xmlns=\"http://www.w3.org/2000/svg\" d=\"M531.9055923136791,948.4902017911274v53.803793867429135h69.04013967147826v-53.803793867429135z\" fill=\"none\" stroke=\"#bfeeb7\" stroke-opacity=\"1.0\" stroke-width=\"2\"/><path xmlns=\"http://www.w3.org/2000/svg\" d=\"M646.9724917661429,948.4902017911274v53.803793867429135h322.18731846689855v-53.803793867429135z\" fill=\"none\" stroke=\"#bfeeb7\" stroke-opacity=\"1.0\" stroke-width=\"2\"/><path xmlns=\"http://www.w3.org/2000/svg\" d=\"M1084.2267096855053,948.4902017911274v53.803793867429135h46.02675978098546v-53.803793867429135z\" fill=\"none\" stroke=\"#feca74\" stroke-opacity=\"1.0\" stroke-width=\"2\"/><path xmlns=\"http://www.w3.org/2000/svg\" d=\"M1199.293609137969,948.4902017911274v53.803793867429135h368.2140782478839v-53.803793867429135z\" fill=\"none\" stroke=\"#bfeeb7\" stroke-opacity=\"1.0\" stroke-width=\"2\"/></svg>"
        }
      }
    },
    {
      "id": "https://gallica.bnf.fr/iiif/ark:/12148/bpt6k62929887/p345-tag-2007",
      "type": "Annotation",
      "motivation": "tagging",
      "body": {
        "type": "TextualBody",
        "value": "Davaine, rue des Lavandi\u00e8res, n.\u00b0 4,\u2014du Mus\u00e9um.\n",
        "format": "text/plain",
        "language": "fr"
      },
      "target": {
        "type": "SpecificResource",
        "source": "https://gallica.bnf.fr/iiif/ark:/12148/bpt6k62929887/p345",
        "selector": {
          "type": "SvgSelector",
          "value": "<svg xmlns=\"http://www.w3.org/2000/svg\"><path xmlns=\"http://www.w3.org/2000/svg\" d=\"M440.71024344436006,992.6207313736279v54.04456571737933h1177.3073692105834v-54.04456571737933z\" fill=\"none\" stroke=\"#ff0000\" stroke-opacity=\"0.2\" stroke-width=\"4\"/><path xmlns=\"http://www.w3.org/2000/svg\" d=\"M440.71024344436006,992.6207313736279v54.04456571737933h175.34365073349113v-54.04456571737933z\" fill=\"none\" stroke=\"#7aecec\" stroke-opacity=\"1.0\" stroke-width=\"2\"/><path xmlns=\"http://www.w3.org/2000/svg\" d=\"M666.1520801017058,992.6207313736279v54.04456571737933h475.93276627661874v-54.04456571737933z\" fill=\"none\" stroke=\"#bfeeb7\" stroke-opacity=\"1.0\" stroke-width=\"2\"/><path xmlns=\"http://www.w3.org/2000/svg\" d=\"M1292.3794041498886,992.6207313736279v54.04456571737933h25.04909296192716v-54.04456571737933z\" fill=\"none\" stroke=\"#feca74\" stroke-opacity=\"1.0\" stroke-width=\"2\"/><path xmlns=\"http://www.w3.org/2000/svg\" d=\"M1367.5266830356704,992.6207313736279v54.04456571737933h225.4418366573458v-54.04456571737933z\" fill=\"none\" stroke=\"#bfeeb7\" stroke-opacity=\"1.0\" stroke-width=\"2\"/></svg>"
        }
      }
    },
    {
      "id": "https://gallica.bnf.fr/iiif/ark:/12148/bpt6k62929887/p345-tag-2008",
      "type": "Annotation",
      "motivation": "tagging",
      "body": {
        "type": "TextualBody",
        "value": "Davy, place Sorbonne, n.\" 420, \u2014des Thermes.\n",
        "format": "text/plain",
        "language": "fr"
      },
      "target": {
        "type": "SpecificResource",
        "source": "https://gallica.bnf.fr/iiif/ark:/12148/bpt6k62929887/p345",
        "selector": {
          "type": "SvgSelector",
          "value": "<svg xmlns=\"http://www.w3.org/2000/svg\"><path xmlns=\"http://www.w3.org/2000/svg\" d=\"M441.61960179674617,1039.3924061457315v54.5701803763709h1062.9093123783798v-54.5701803763709z\" fill=\"none\" stroke=\"#ff0000\" stroke-opacity=\"0.2\" stroke-width=\"4\"/><path xmlns=\"http://www.w3.org/2000/svg\" d=\"M441.61960179674617,1039.3924061457315v54.5701803763709h96.62811930712544v-54.5701803763709z\" fill=\"none\" stroke=\"#7aecec\" stroke-opacity=\"1.0\" stroke-width=\"2\"/><path xmlns=\"http://www.w3.org/2000/svg\" d=\"M586.5617807574343,1039.3924061457315v54.5701803763709h338.19841757493907v-54.5701803763709z\" fill=\"none\" stroke=\"#bfeeb7\" stroke-opacity=\"1.0\" stroke-width=\"2\"/><path xmlns=\"http://www.w3.org/2000/svg\" d=\"M1069.7023772930615,1039.3924061457315v54.5701803763709h72.47108948034406v-54.5701803763709z\" fill=\"none\" stroke=\"#feca74\" stroke-opacity=\"1.0\" stroke-width=\"2\"/><path xmlns=\"http://www.w3.org/2000/svg\" d=\"M1214.6445562537497,1039.3924061457315v54.5701803763709h265.7273280945949v-54.5701803763709z\" fill=\"none\" stroke=\"#bfeeb7\" stroke-opacity=\"1.0\" stroke-width=\"2\"/></svg>"
        }
      }
    },
    {
      "id": "https://gallica.bnf.fr/iiif/ark:/12148/bpt6k62929887/p345-tag-2009",
      "type": "Annotation",
      "motivation": "tagging",
      "body": {
        "type": "TextualBody",
        "value": "Debruyere, rue des Boucheries, n.\u00b0 95, \u2014du Luxembourg.\n",
        "format": "text/plain",
        "language": "fr"
      },
      "target": {
        "type": "SpecificResource",
        "source": "https://gallica.bnf.fr/iiif/ark:/12148/bpt6k62929887/p345",
        "selector": {
          "type": "SvgSelector",
          "value": "<svg xmlns=\"http://www.w3.org/2000/svg\"><path xmlns=\"http://www.w3.org/2000/svg\" d=\"M442.5386904286309,1086.650542140007v54.684964060783386h1314.059060272487v-54.684964060783386z\" fill=\"none\" stroke=\"#ff0000\" stroke-opacity=\"0.2\" stroke-width=\"4\"/><path xmlns=\"http://www.w3.org/2000/svg\" d=\"M442.5386904286309,1086.650542140007v54.684964060783386h219.0098433787478v-54.684964060783386z\" fill=\"none\" stroke=\"#7aecec\" stroke-opacity=\"1.0\" stroke-width=\"2\"/><path xmlns=\"http://www.w3.org/2000/svg\" d=\"M710.2173878915448,1086.650542140007v54.684964060783386h438.0196867574957v-54.684964060783386z\" fill=\"none\" stroke=\"#bfeeb7\" stroke-opacity=\"1.0\" stroke-width=\"2\"/><path xmlns=\"http://www.w3.org/2000/svg\" d=\"M1294.243636901539,1086.650542140007v54.684964060783386h48.66885408416624v-54.684964060783386z\" fill=\"none\" stroke=\"#feca74\" stroke-opacity=\"1.0\" stroke-width=\"2\"/><path xmlns=\"http://www.w3.org/2000/svg\" d=\"M1415.9157721119545,1086.650542140007v54.684964060783386h316.34755154708034v-54.684964060783386z\" fill=\"none\" stroke=\"#bfeeb7\" stroke-opacity=\"1.0\" stroke-width=\"2\"/></svg>"
        }
      }
    },
    {
      "id": "https://gallica.bnf.fr/iiif/ark:/12148/bpt6k62929887/p345-tag-2010",
      "type": "Annotation",
      "motivation": "tagging",
      "body": {
        "type": "TextualBody",
        "value": "Dechilly, rue Notre-Dame-de-Recouvrance, n.\u00b0 134, \u2014du\n",
        "format": "text/plain",
        "language": "fr"
      },
      "target": {
        "type": "SpecificResource",
        "source": "https://gallica.bnf.fr/iiif/ark:/12148/bpt6k62929887/p345",
        "selector": {
          "type": "SvgSelector",
          "value": "<svg xmlns=\"http://www.w3.org/2000/svg\"><path xmlns=\"http://www.w3.org/2000/svg\" d=\"M443.4694256058584,1134.4844117629054v57.075118833033h1360.9850469316725v-57.075118833033z\" fill=\"none\" stroke=\"#ff0000\" stroke-opacity=\"0.2\" stroke-width=\"4\"/><path xmlns=\"http://www.w3.org/2000/svg\" d=\"M443.4694256058584,1134.4844117629054v57.075118833033h205.43170519723358v-57.075118833033z\" fill=\"none\" stroke=\"#7aecec\" stroke-opacity=\"1.0\" stroke-width=\"2\"/><path xmlns=\"http://www.w3.org/2000/svg\" d=\"M700.2590571024004,1134.4844117629054v57.075118833033h744.6899313399716v-57.075118833033z\" fill=\"none\" stroke=\"#bfeeb7\" stroke-opacity=\"1.0\" stroke-width=\"2\"/><path xmlns=\"http://www.w3.org/2000/svg\" d=\"M1599.0227673402974,1134.4844117629054v57.075118833033h51.35792629930825v-57.075118833033z\" fill=\"none\" stroke=\"#feca74\" stroke-opacity=\"1.0\" stroke-width=\"2\"/><path xmlns=\"http://www.w3.org/2000/svg\" d=\"M1753.0965462382223,1134.4844117629054v57.075118833033h51.357926299308474v-57.075118833033z\" fill=\"none\" stroke=\"#bfeeb7\" stroke-opacity=\"1.0\" stroke-width=\"2\"/></svg>"
        }
      }
    },
    {
      "id": "https://gallica.bnf.fr/iiif/ark:/12148/bpt6k62929887/p345-tag-2012",
      "type": "Annotation",
      "motivation": "tagging",
      "body": {
        "type": "TextualBody",
        "value": "D\u00e9court, rue du Temple, n.\u00b0 126,\u2014des Gravilliers.\n",
        "format": "text/plain",
        "language": "fr"
      },
      "target": {
        "type": "SpecificResource",
        "source": "https://gallica.bnf.fr/iiif/ark:/12148/bpt6k62929887/p345",
        "selector": {
          "type": "SvgSelector",
          "value": "<svg xmlns=\"http://www.w3.org/2000/svg\"><path xmlns=\"http://www.w3.org/2000/svg\" d=\"M445.30397355416704,1228.8042840560277v54.058758060137734h1183.373993683028v-54.058758060137734z\" fill=\"none\" stroke=\"#ff0000\" stroke-opacity=\"0.2\" stroke-width=\"4\"/><path xmlns=\"http://www.w3.org/2000/svg\" d=\"M445.30397355416704,1228.8042840560277v54.058758060137734h48.300979334001134v-54.058758060137734z\" fill=\"none\" stroke=\"#7aecec\" stroke-opacity=\"1.0\" stroke-width=\"2\"/><path xmlns=\"http://www.w3.org/2000/svg\" d=\"M493.60495288816816,1228.8042840560277v54.058758060137734h120.75244833500284v-54.058758060137734z\" fill=\"none\" stroke=\"#bfeeb7\" stroke-opacity=\"1.0\" stroke-width=\"2\"/><path xmlns=\"http://www.w3.org/2000/svg\" d=\"M662.6583805571722,1228.8042840560277v54.058758060137734h313.95636567100746v-54.058758060137734z\" fill=\"none\" stroke=\"#bfeeb7\" stroke-opacity=\"1.0\" stroke-width=\"2\"/><path xmlns=\"http://www.w3.org/2000/svg\" d=\"M1121.517684230183,1228.8042840560277v54.058758060137734h72.45146900100178v-54.058758060137734z\" fill=\"none\" stroke=\"#feca74\" stroke-opacity=\"1.0\" stroke-width=\"2\"/><path xmlns=\"http://www.w3.org/2000/svg\" d=\"M1242.2701325651858,1228.8042840560277v54.058758060137734h362.2573450050086v-54.058758060137734z\" fill=\"none\" stroke=\"#bfeeb7\" stroke-opacity=\"1.0\" stroke-width=\"2\"/></svg>"
        }
      }
    },
    {
      "id": "https://gallica.bnf.fr/iiif/ark:/12148/bpt6k62929887/p345-tag-2013",
      "type": "Annotation",
      "motivation": "tagging",
      "body": {
        "type": "TextualBody",
        "value": "Dejob, vieille rue du Temple, n.\u00b0 717,\u2014de l'Indivisibilit\u00e9.\n",
        "format": "text/plain",
        "language": "fr"
      },
      "target": {
        "type": "SpecificResource",
        "source": "https://gallica.bnf.fr/iiif/ark:/12148/bpt6k62929887/p345",
        "selector": {
          "type": "SvgSelector",
          "value": "<svg xmlns=\"http://www.w3.org/2000/svg\"><path xmlns=\"http://www.w3.org/2000/svg\" d=\"M446.2247251792986,1276.1442127625146v51.107124249140725h1331.1486298753698v-51.107124249140725z\" fill=\"none\" stroke=\"#ff0000\" stroke-opacity=\"0.2\" stroke-width=\"4\"/><path xmlns=\"http://www.w3.org/2000/svg\" d=\"M446.2247251792986,1276.1442127625146v51.107124249140725h112.8092059216415v-51.107124249140725z\" fill=\"none\" stroke=\"#7aecec\" stroke-opacity=\"1.0\" stroke-width=\"2\"/><path xmlns=\"http://www.w3.org/2000/svg\" d=\"M604.1576134695968,1276.1442127625146v51.107124249140725h473.7986648708943v-51.107124249140725z\" fill=\"none\" stroke=\"#bfeeb7\" stroke-opacity=\"1.0\" stroke-width=\"2\"/><path xmlns=\"http://www.w3.org/2000/svg\" d=\"M1213.327325446461,1276.1442127625146v51.107124249140725h67.68552355298482v-51.107124249140725z\" fill=\"none\" stroke=\"#feca74\" stroke-opacity=\"1.0\" stroke-width=\"2\"/><path xmlns=\"http://www.w3.org/2000/svg\" d=\"M1326.1365313681024,1276.1442127625146v51.107124249140725h428.67498250223787v-51.107124249140725z\" fill=\"none\" stroke=\"#bfeeb7\" stroke-opacity=\"1.0\" stroke-width=\"2\"/></svg>"
        }
      }
    },
    {
      "id": "https://gallica.bnf.fr/iiif/ark:/12148/bpt6k62929887/p345-tag-2014",
      "type": "Annotation",
      "motivation": "tagging",
      "body": {
        "type": "TextualBody",
        "value": "Dehaye, rue neuve Augustin, n.\u00b0 914,\u2014de Pelletier.\n",
        "format": "text/plain",
        "language": "fr"
      },
      "target": {
        "type": "SpecificResource",
        "source": "https://gallica.bnf.fr/iiif/ark:/12148/bpt6k62929887/p345",
        "selector": {
          "type": "SvgSelector",
          "value": "<svg xmlns=\"http://www.w3.org/2000/svg\"><path xmlns=\"http://www.w3.org/2000/svg\" d=\"M447.1012120053306,1321.184864731421v53.368305750896525h1180.4638184943544v-53.368305750896525z\" fill=\"none\" stroke=\"#ff0000\" stroke-opacity=\"0.2\" stroke-width=\"4\"/><path xmlns=\"http://www.w3.org/2000/svg\" d=\"M447.1012120053306,1321.184864731421v53.368305750896525h141.65565821932253v-53.368305750896525z\" fill=\"none\" stroke=\"#7aecec\" stroke-opacity=\"1.0\" stroke-width=\"2\"/><path xmlns=\"http://www.w3.org/2000/svg\" d=\"M635.9754229644273,1321.184864731421v53.368305750896525h424.9669746579676v-53.368305750896525z\" fill=\"none\" stroke=\"#bfeeb7\" stroke-opacity=\"1.0\" stroke-width=\"2\"/><path xmlns=\"http://www.w3.org/2000/svg\" d=\"M1202.5980558417173,1321.184864731421v53.368305750896525h70.82782910966125v-53.368305750896525z\" fill=\"none\" stroke=\"#feca74\" stroke-opacity=\"1.0\" stroke-width=\"2\"/><path xmlns=\"http://www.w3.org/2000/svg\" d=\"M1320.6444376911527,1321.184864731421v53.368305750896525h283.3113164386451v-53.368305750896525z\" fill=\"none\" stroke=\"#bfeeb7\" stroke-opacity=\"1.0\" stroke-width=\"2\"/></svg>"
        }
      }
    },
    {
      "id": "https://gallica.bnf.fr/iiif/ark:/12148/bpt6k62929887/p345-tag-2015",
      "type": "Annotation",
      "motivation": "tagging",
      "body": {
        "type": "TextualBody",
        "value": "Del\u00e9tang, faubourg Antoine, n.\u00b0 189, \u2014des Quinze-Vingts.\n",
        "format": "text/plain",
        "language": "fr"
      },
      "target": {
        "type": "SpecificResource",
        "source": "https://gallica.bnf.fr/iiif/ark:/12148/bpt6k62929887/p345",
        "selector": {
          "type": "SvgSelector",
          "value": "<svg xmlns=\"http://www.w3.org/2000/svg\"><path xmlns=\"http://www.w3.org/2000/svg\" d=\"M448.01739221267934,1368.3035598993301v50.82539379596733h1335.6208303151648v-50.82539379596733z\" fill=\"none\" stroke=\"#ff0000\" stroke-opacity=\"0.2\" stroke-width=\"4\"/><path xmlns=\"http://www.w3.org/2000/svg\" d=\"M448.01739221267934,1368.3035598993301v50.82539379596733h190.80297575930925v-50.82539379596733z\" fill=\"none\" stroke=\"#7aecec\" stroke-opacity=\"1.0\" stroke-width=\"2\"/><path xmlns=\"http://www.w3.org/2000/svg\" d=\"M686.521111911816,1368.3035598993301v50.82539379596733h381.60595151861855v-50.82539379596733z\" fill=\"none\" stroke=\"#bfeeb7\" stroke-opacity=\"1.0\" stroke-width=\"2\"/><path xmlns=\"http://www.w3.org/2000/svg\" d=\"M1211.2292952499163,1368.3035598993301v50.82539379596733h71.55111590974104v-50.82539379596733z\" fill=\"none\" stroke=\"#feca74\" stroke-opacity=\"1.0\" stroke-width=\"2\"/><path xmlns=\"http://www.w3.org/2000/svg\" d=\"M1354.3315270693984,1368.3035598993301v50.82539379596733h405.456323488532v-50.82539379596733z\" fill=\"none\" stroke=\"#bfeeb7\" stroke-opacity=\"1.0\" stroke-width=\"2\"/></svg>"
        }
      }
    },
    {
      "id": "https://gallica.bnf.fr/iiif/ark:/12148/bpt6k62929887/p345-tag-2016",
      "type": "Annotation",
      "motivation": "tagging",
      "body": {
        "type": "TextualBody",
        "value": "Delmotte, rue de Charenton, n.\u00b0 194, \u2014des Quinze-Vingts.\n",
        "format": "text/plain",
        "language": "fr"
      },
      "target": {
        "type": "SpecificResource",
        "source": "https://gallica.bnf.fr/iiif/ark:/12148/bpt6k62929887/p345",
        "selector": {
          "type": "SvgSelector",
          "value": "<svg xmlns=\"http://www.w3.org/2000/svg\"><path xmlns=\"http://www.w3.org/2000/svg\" d=\"M448.93869350951496,1415.6682629585266v53.68129154046369h1337.081023547355v-53.68129154046369z\" fill=\"none\" stroke=\"#ff0000\" stroke-opacity=\"0.2\" stroke-width=\"4\"/><path xmlns=\"http://www.w3.org/2000/svg\" d=\"M448.93869350951496,1415.6682629585266v53.68129154046369h191.01157479247928v-53.68129154046369z\" fill=\"none\" stroke=\"#7aecec\" stroke-opacity=\"1.0\" stroke-width=\"2\"/><path xmlns=\"http://www.w3.org/2000/svg\" d=\"M687.703162000114,1415.6682629585266v53.68129154046369h382.02314958495856v-53.68129154046369z\" fill=\"none\" stroke=\"#bfeeb7\" stroke-opacity=\"1.0\" stroke-width=\"2\"/><path xmlns=\"http://www.w3.org/2000/svg\" d=\"M1212.984992679432,1415.6682629585266v53.68129154046369h47.752893698119806v-53.68129154046369z\" fill=\"none\" stroke=\"#feca74\" stroke-opacity=\"1.0\" stroke-width=\"2\"/><path xmlns=\"http://www.w3.org/2000/svg\" d=\"M1356.2436737737917,1415.6682629585266v53.68129154046369h405.89959643401846v-53.68129154046369z\" fill=\"none\" stroke=\"#bfeeb7\" stroke-opacity=\"1.0\" stroke-width=\"2\"/></svg>"
        }
      }
    },
    {
      "id": "https://gallica.bnf.fr/iiif/ark:/12148/bpt6k62929887/p345-tag-2017",
      "type": "Annotation",
      "motivation": "tagging",
      "body": {
        "type": "TextualBody",
        "value": "Delpech, faubourg Denis, n. 10, \u2014Poissonni\u00e8re.\n",
        "format": "text/plain",
        "language": "fr"
      },
      "target": {
        "type": "SpecificResource",
        "source": "https://gallica.bnf.fr/iiif/ark:/12148/bpt6k62929887/p345",
        "selector": {
          "type": "SvgSelector",
          "value": "<svg xmlns=\"http://www.w3.org/2000/svg\"><path xmlns=\"http://www.w3.org/2000/svg\" d=\"M449.871023290014,1462.8363896210988v50.845312873522516h1127.281841553528v-50.845312873522516z\" fill=\"none\" stroke=\"#ff0000\" stroke-opacity=\"0.2\" stroke-width=\"4\"/><path xmlns=\"http://www.w3.org/2000/svg\" d=\"M449.871023290014,1462.8363896210988v50.845312873522516h171.54288893205862v-50.845312873522516z\" fill=\"none\" stroke=\"#7aecec\" stroke-opacity=\"1.0\" stroke-width=\"2\"/><path xmlns=\"http://www.w3.org/2000/svg\" d=\"M670.4261662026609,1462.8363896210988v50.845312873522516h343.0857778641172v-50.845312873522516z\" fill=\"none\" stroke=\"#bfeeb7\" stroke-opacity=\"1.0\" stroke-width=\"2\"/><path xmlns=\"http://www.w3.org/2000/svg\" d=\"M1136.0425790182485,1462.8363896210988v50.845312873522516h49.012253980588184v-50.845312873522516z\" fill=\"none\" stroke=\"#feca74\" stroke-opacity=\"1.0\" stroke-width=\"2\"/><path xmlns=\"http://www.w3.org/2000/svg\" d=\"M1258.5732139697188,1462.8363896210988v50.845312873522516h294.0735238835292v-50.845312873522516z\" fill=\"none\" stroke=\"#bfeeb7\" stroke-opacity=\"1.0\" stroke-width=\"2\"/></svg>"
        }
      }
    },
    {
      "id": "https://gallica.bnf.fr/iiif/ark:/12148/bpt6k62929887/p345-tag-2018",
      "type": "Annotation",
      "motivation": "tagging",
      "body": {
        "type": "TextualBody",
        "value": "Delvall\u00e9e, rue Baillif, n.\u00b0 15,\u2014de la Halle-au-Bled.\n",
        "format": "text/plain",
        "language": "fr"
      },
      "target": {
        "type": "SpecificResource",
        "source": "https://gallica.bnf.fr/iiif/ark:/12148/bpt6k62929887/p345",
        "selector": {
          "type": "SvgSelector",
          "value": "<svg xmlns=\"http://www.w3.org/2000/svg\"><path xmlns=\"http://www.w3.org/2000/svg\" d=\"M450.756498330935,1506.8841927846272v54.19507924715731h1178.364085291525v-54.19507924715731z\" fill=\"none\" stroke=\"#ff0000\" stroke-opacity=\"0.2\" stroke-width=\"4\"/><path xmlns=\"http://www.w3.org/2000/svg\" d=\"M450.756498330935,1506.8841927846272v54.19507924715731h203.9476301466101v-54.19507924715731z\" fill=\"none\" stroke=\"#7aecec\" stroke-opacity=\"1.0\" stroke-width=\"2\"/><path xmlns=\"http://www.w3.org/2000/svg\" d=\"M700.0258240656807,1506.8841927846272v54.19507924715731h249.26932573474568v-54.19507924715731z\" fill=\"none\" stroke=\"#bfeeb7\" stroke-opacity=\"1.0\" stroke-width=\"2\"/><path xmlns=\"http://www.w3.org/2000/svg\" d=\"M1085.2602365648331,1506.8841927846272v54.19507924715731h45.321695588135526v-54.19507924715731z\" fill=\"none\" stroke=\"#feca74\" stroke-opacity=\"1.0\" stroke-width=\"2\"/><path xmlns=\"http://www.w3.org/2000/svg\" d=\"M1175.9036277411044,1506.8841927846272v54.19507924715731h430.55610808728784v-54.19507924715731z\" fill=\"none\" stroke=\"#bfeeb7\" stroke-opacity=\"1.0\" stroke-width=\"2\"/></svg>"
        }
      }
    },
    {
      "id": "https://gallica.bnf.fr/iiif/ark:/12148/bpt6k62929887/p345-tag-2019",
      "type": "Annotation",
      "motivation": "tagging",
      "body": {
        "type": "TextualBody",
        "value": "Delion, rue du Chantre, n.\u00b0 77,\u2014des Gardes-Fran\u00e7aises.\n",
        "format": "text/plain",
        "language": "fr"
      },
      "target": {
        "type": "SpecificResource",
        "source": "https://gallica.bnf.fr/iiif/ark:/12148/bpt6k62929887/p345",
        "selector": {
          "type": "SvgSelector",
          "value": "<svg xmlns=\"http://www.w3.org/2000/svg\"><path xmlns=\"http://www.w3.org/2000/svg\" d=\"M451.7081085825356,1554.2218805948894v54.26243062814092h1284.721698751097v-54.26243062814092z\" fill=\"none\" stroke=\"#ff0000\" stroke-opacity=\"0.2\" stroke-width=\"4\"/><path xmlns=\"http://www.w3.org/2000/svg\" d=\"M451.7081085825356,1554.2218805948894v54.26243062814092h142.74685541678855v-54.26243062814092z\" fill=\"none\" stroke=\"#7aecec\" stroke-opacity=\"1.0\" stroke-width=\"2\"/><path xmlns=\"http://www.w3.org/2000/svg\" d=\"M642.0372491382536,1554.2218805948894v54.26243062814092h333.0759959725066v-54.26243062814092z\" fill=\"none\" stroke=\"#bfeeb7\" stroke-opacity=\"1.0\" stroke-width=\"2\"/><path xmlns=\"http://www.w3.org/2000/svg\" d=\"M1117.8601005275486,1554.2218805948894v54.26243062814092h47.58228513892959v-54.26243062814092z\" fill=\"none\" stroke=\"#feca74\" stroke-opacity=\"1.0\" stroke-width=\"2\"/><path xmlns=\"http://www.w3.org/2000/svg\" d=\"M1213.0246708054078,1554.2218805948894v54.26243062814092h499.61399395876003v-54.26243062814092z\" fill=\"none\" stroke=\"#bfeeb7\" stroke-opacity=\"1.0\" stroke-width=\"2\"/></svg>"
        }
      }
    },
    {
      "id": "https://gallica.bnf.fr/iiif/ark:/12148/bpt6k62929887/p345-tag-2020",
      "type": "Annotation",
      "motivation": "tagging",
      "body": {
        "type": "TextualBody",
        "value": "Demay, rue de Cl\u00e9ry, n.\u00b0 259, \u2014de Bonne-Nouvelle.\nDemay, rue Hauteville, n \u00b0 18,\u2014Poissonni\u00e8re.\nDemorgny, rue de la Harpe, n.\u00b0 171,\u2014du Th\u00e9\u00e2tre-Fran\u00e7ais.\n",
        "format": "text/plain",
        "language": "fr"
      },
      "target": {
        "type": "SpecificResource",
        "source": "https://gallica.bnf.fr/iiif/ark:/12148/bpt6k62929887/p345",
        "selector": {
          "type": "SvgSelector",
          "value": "<svg xmlns=\"http://www.w3.org/2000/svg\"><path xmlns=\"http://www.w3.org/2000/svg\" d=\"M452.66178102340433,1601.6621516545613v145.83615688482928h1347.9399842893213v-145.83615688482928z\" fill=\"none\" stroke=\"#ff0000\" stroke-opacity=\"0.2\" stroke-width=\"4\"/><path xmlns=\"http://www.w3.org/2000/svg\" d=\"M452.66178102340433,1601.6621516545613v53.95144402980827h124.46001286910824v-53.95144402980827z\" fill=\"none\" stroke=\"#7aecec\" stroke-opacity=\"1.0\" stroke-width=\"2\"/><path xmlns=\"http://www.w3.org/2000/svg\" d=\"M626.9057990401559,1601.6621516545613v53.95144402980827h298.70403088585977v-53.95144402980827z\" fill=\"none\" stroke=\"#bfeeb7\" stroke-opacity=\"1.0\" stroke-width=\"2\"/><path xmlns=\"http://www.w3.org/2000/svg\" d=\"M1074.9618453689454,1601.6621516545613v53.95144402980827h74.67600772146488v-53.95144402980827z\" fill=\"none\" stroke=\"#feca74\" stroke-opacity=\"1.0\" stroke-width=\"2\"/><path xmlns=\"http://www.w3.org/2000/svg\" d=\"M1224.3138608118754,1601.6621516545613v53.95144402980827h423.164043754968v-53.95144402980827z\" fill=\"none\" stroke=\"#bfeeb7\" stroke-opacity=\"1.0\" stroke-width=\"2\"/><path xmlns=\"http://www.w3.org/2000/svg\" d=\"M452.66178102340433,1601.6621516545613v53.95144402980827h124.46001286910824v-53.95144402980827z\" fill=\"none\" stroke=\"#7aecec\" stroke-opacity=\"1.0\" stroke-width=\"2\"/><path xmlns=\"http://www.w3.org/2000/svg\" d=\"M622.6009193903913,1648.6170196930568v51.20945851008105h337.9904475705772v-51.20945851008105z\" fill=\"none\" stroke=\"#bfeeb7\" stroke-opacity=\"1.0\" stroke-width=\"2\"/><path xmlns=\"http://www.w3.org/2000/svg\" d=\"M1105.4444159197872,1648.6170196930568v51.20945851008105h48.28434965293957v-51.20945851008105z\" fill=\"none\" stroke=\"#feca74\" stroke-opacity=\"1.0\" stroke-width=\"2\"/><path xmlns=\"http://www.w3.org/2000/svg\" d=\"M1202.0131152256663,1648.6170196930568v51.20945851008105h289.70609791763763v-51.20945851008105z\" fill=\"none\" stroke=\"#bfeeb7\" stroke-opacity=\"1.0\" stroke-width=\"2\"/><path xmlns=\"http://www.w3.org/2000/svg\" d=\"M454.5561721531371,1695.8983116149902v51.59999692440033h192.29222759422692v-51.59999692440033z\" fill=\"none\" stroke=\"#7aecec\" stroke-opacity=\"1.0\" stroke-width=\"2\"/><path xmlns=\"http://www.w3.org/2000/svg\" d=\"M694.9214566459207,1695.8983116149902v51.59999692440033h360.5479267391755v-51.59999692440033z\" fill=\"none\" stroke=\"#bfeeb7\" stroke-opacity=\"1.0\" stroke-width=\"2\"/><path xmlns=\"http://www.w3.org/2000/svg\" d=\"M1199.6885540807664,1695.8983116149902v51.59999692440033h48.07305689855673v-51.59999692440033z\" fill=\"none\" stroke=\"#feca74\" stroke-opacity=\"1.0\" stroke-width=\"2\"/><path xmlns=\"http://www.w3.org/2000/svg\" d=\"M1319.8711963271583,1695.8983116149902v51.59999692440033h456.69404053628875v-51.59999692440033z\" fill=\"none\" stroke=\"#bfeeb7\" stroke-opacity=\"1.0\" stroke-width=\"2\"/></svg>"
        }
      }
    },
    {
      "id": "https://gallica.bnf.fr/iiif/ark:/12148/bpt6k62929887/p345-tag-2021",
      "type": "Annotation",
      "motivation": "tagging",
      "body": {
        "type": "TextualBody",
        "value": "Denant, rue Gallande, n. 4,\u2014du Panth\u00e9on.\nDenis, clo\u00eetre Nicolas, n.\u00b0 6, \u2014des Thuileries.\n",
        "format": "text/plain",
        "language": "fr"
      },
      "target": {
        "type": "SpecificResource",
        "source": "https://gallica.bnf.fr/iiif/ark:/12148/bpt6k62929887/p345",
        "selector": {
          "type": "SvgSelector",
          "value": "<svg xmlns=\"http://www.w3.org/2000/svg\"><path xmlns=\"http://www.w3.org/2000/svg\" d=\"M455.4493478692742,1740.329183538755v101.59090586503339h1051.4442794981205v-101.59090586503339z\" fill=\"none\" stroke=\"#ff0000\" stroke-opacity=\"0.2\" stroke-width=\"4\"/><path xmlns=\"http://www.w3.org/2000/svg\" d=\"M455.4493478692742,1740.329183538755v54.08863667647029h150.92226231417465v-54.08863667647029z\" fill=\"none\" stroke=\"#7aecec\" stroke-opacity=\"1.0\" stroke-width=\"2\"/><path xmlns=\"http://www.w3.org/2000/svg\" d=\"M656.6790309548404,1740.329183538755v54.08863667647029h301.8445246283493v-54.08863667647029z\" fill=\"none\" stroke=\"#bfeeb7\" stroke-opacity=\"1.0\" stroke-width=\"2\"/><path xmlns=\"http://www.w3.org/2000/svg\" d=\"M1084.2921075116687,1740.329183538755v54.08863667647029h25.15371038569583v-54.08863667647029z\" fill=\"none\" stroke=\"#feca74\" stroke-opacity=\"1.0\" stroke-width=\"2\"/><path xmlns=\"http://www.w3.org/2000/svg\" d=\"M1159.7532386687558,1740.329183538755v54.08863667647029h276.6908142426536v-54.08863667647029z\" fill=\"none\" stroke=\"#bfeeb7\" stroke-opacity=\"1.0\" stroke-width=\"2\"/><path xmlns=\"http://www.w3.org/2000/svg\" d=\"M456.17397261992136,1787.6835535764694v54.2365358273189h491.82622137115766v-54.2365358273189z\" fill=\"none\" stroke=\"#bfeeb7\" stroke-opacity=\"1.0\" stroke-width=\"2\"/><path xmlns=\"http://www.w3.org/2000/svg\" d=\"M1082.1346180013948,1787.6835535764694v54.2365358273189h22.35573733505271v-54.2365358273189z\" fill=\"none\" stroke=\"#feca74\" stroke-opacity=\"1.0\" stroke-width=\"2\"/><path xmlns=\"http://www.w3.org/2000/svg\" d=\"M1171.5575673416051,1787.6835535764694v54.2365358273189h312.98032269073667v-54.2365358273189z\" fill=\"none\" stroke=\"#bfeeb7\" stroke-opacity=\"1.0\" stroke-width=\"2\"/></svg>"
        }
      }
    },
    {
      "id": "https://gallica.bnf.fr/iiif/ark:/12148/bpt6k62929887/p345-tag-2022",
      "type": "Annotation",
      "motivation": "tagging",
      "body": {
        "type": "TextualBody",
        "value": "Desfontaine, rue de Braque, n.\u00b0 20, \u2014de l'Homme-Arm\u00e9.\n",
        "format": "text/plain",
        "language": "fr"
      },
      "target": {
        "type": "SpecificResource",
        "source": "https://gallica.bnf.fr/iiif/ark:/12148/bpt6k62929887/p345",
        "selector": {
          "type": "SvgSelector",
          "value": "<svg xmlns=\"http://www.w3.org/2000/svg\"><path xmlns=\"http://www.w3.org/2000/svg\" d=\"M457.09232571408444,1834.8978676001232v54.1703048944471h1319.7507937111773v-54.1703048944471z\" fill=\"none\" stroke=\"#ff0000\" stroke-opacity=\"0.2\" stroke-width=\"4\"/><path xmlns=\"http://www.w3.org/2000/svg\" d=\"M457.09232571408444,1834.8978676001232v54.1703048944471h273.91054209099906v-54.1703048944471z\" fill=\"none\" stroke=\"#7aecec\" stroke-opacity=\"1.0\" stroke-width=\"2\"/><path xmlns=\"http://www.w3.org/2000/svg\" d=\"M780.8047845489016,1834.8978676001232v54.1703048944471h323.7124588348171v-54.1703048944471z\" fill=\"none\" stroke=\"#bfeeb7\" stroke-opacity=\"1.0\" stroke-width=\"2\"/><path xmlns=\"http://www.w3.org/2000/svg\" d=\"M1253.9229936151726,1834.8978676001232v54.1703048944471h49.80191674381808v-54.1703048944471z\" fill=\"none\" stroke=\"#feca74\" stroke-opacity=\"1.0\" stroke-width=\"2\"/><path xmlns=\"http://www.w3.org/2000/svg\" d=\"M1378.4277854747177,1834.8978676001232v54.1703048944471h373.51437557863517v-54.1703048944471z\" fill=\"none\" stroke=\"#bfeeb7\" stroke-opacity=\"1.0\" stroke-width=\"2\"/></svg>"
        }
      }
    },
    {
      "id": "https://gallica.bnf.fr/iiif/ark:/12148/bpt6k62929887/p345-tag-2023",
      "type": "Annotation",
      "motivation": "tagging",
      "body": {
        "type": "TextualBody",
        "value": "Deshayes, rue de Bondy, n.\u00b0 16,\u2014de Bondy.\n",
        "format": "text/plain",
        "language": "fr"
      },
      "target": {
        "type": "SpecificResource",
        "source": "https://gallica.bnf.fr/iiif/ark:/12148/bpt6k62929887/p345",
        "selector": {
          "type": "SvgSelector",
          "value": "<svg xmlns=\"http://www.w3.org/2000/svg\"><path xmlns=\"http://www.w3.org/2000/svg\" d=\"M458.3099722747504,1882.6304511229196v50.73862131436658h1027.0936652299388v-50.73862131436658z\" fill=\"none\" stroke=\"#ff0000\" stroke-opacity=\"0.2\" stroke-width=\"4\"/><path xmlns=\"http://www.w3.org/2000/svg\" d=\"M458.3099722747504,1882.6304511229196v50.73862131436658h200.40852004486612v-50.73862131436658z\" fill=\"none\" stroke=\"#7aecec\" stroke-opacity=\"1.0\" stroke-width=\"2\"/><path xmlns=\"http://www.w3.org/2000/svg\" d=\"M708.820622330833,1882.6304511229196v50.73862131436658h300.6127800672992v-50.73862131436658z\" fill=\"none\" stroke=\"#bfeeb7\" stroke-opacity=\"1.0\" stroke-width=\"2\"/><path xmlns=\"http://www.w3.org/2000/svg\" d=\"M1159.7397924317818,1882.6304511229196v50.73862131436658h50.102130011216445v-50.73862131436658z\" fill=\"none\" stroke=\"#feca74\" stroke-opacity=\"1.0\" stroke-width=\"2\"/><path xmlns=\"http://www.w3.org/2000/svg\" d=\"M809.0248823532661,1882.6304511229196v50.73862131436658h200.40852004486612v-50.73862131436658z\" fill=\"none\" stroke=\"#bfeeb7\" stroke-opacity=\"1.0\" stroke-width=\"2\"/></svg>"
        }
      }
    },
    {
      "id": "https://gallica.bnf.fr/iiif/ark:/12148/bpt6k62929887/p345-tag-2024",
      "type": "Annotation",
      "motivation": "tagging",
      "body": {
        "type": "TextualBody",
        "value": "Dhollande, rne de Bercy, n.\u00b0 11, \u2014des Droits-de-l'Homme.\n",
        "format": "text/plain",
        "language": "fr"
      },
      "target": {
        "type": "SpecificResource",
        "source": "https://gallica.bnf.fr/iiif/ark:/12148/bpt6k62929887/p345",
        "selector": {
          "type": "SvgSelector",
          "value": "<svg xmlns=\"http://www.w3.org/2000/svg\"><path xmlns=\"http://www.w3.org/2000/svg\" d=\"M458.9784068906819,1926.9630970954895v56.517021218935724h1341.1215738337787v-56.517021218935724z\" fill=\"none\" stroke=\"#ff0000\" stroke-opacity=\"0.2\" stroke-width=\"4\"/><path xmlns=\"http://www.w3.org/2000/svg\" d=\"M458.9784068906819,1926.9630970954895v56.517021218935724h215.53739579471446v-56.517021218935724z\" fill=\"none\" stroke=\"#7aecec\" stroke-opacity=\"1.0\" stroke-width=\"2\"/><path xmlns=\"http://www.w3.org/2000/svg\" d=\"M722.4130017508885,1926.9630970954895v56.517021218935724h287.38319439295253v-56.517021218935724z\" fill=\"none\" stroke=\"#bfeeb7\" stroke-opacity=\"1.0\" stroke-width=\"2\"/><path xmlns=\"http://www.w3.org/2000/svg\" d=\"M1153.4877933403175,1926.9630970954895v56.517021218935724h47.89719906549203v-56.517021218935724z\" fill=\"none\" stroke=\"#feca74\" stroke-opacity=\"1.0\" stroke-width=\"2\"/><path xmlns=\"http://www.w3.org/2000/svg\" d=\"M1273.2307910040474,1926.9630970954895v56.517021218935724h502.920590187667v-56.517021218935724z\" fill=\"none\" stroke=\"#bfeeb7\" stroke-opacity=\"1.0\" stroke-width=\"2\"/></svg>"
        }
      }
    },
    {
      "id": "https://gallica.bnf.fr/iiif/ark:/12148/bpt6k62929887/p345-tag-2025",
      "type": "Annotation",
      "motivation": "tagging",
      "body": {
        "type": "TextualBody",
        "value": "Dhollande, rue des Vieux-Augustins, n.\u00b0 17,\u2014du Mail.\nDimi\u00e9, rue Andr\u00e9-des-Arts, n.\u00b0 50, \u2014du Th\u00e9\u00e2tre-Fran\u00e7ais.\n",
        "format": "text/plain",
        "language": "fr"
      },
      "target": {
        "type": "SpecificResource",
        "source": "https://gallica.bnf.fr/iiif/ark:/12148/bpt6k62929887/p345",
        "selector": {
          "type": "SvgSelector",
          "value": "<svg xmlns=\"http://www.w3.org/2000/svg\"><path xmlns=\"http://www.w3.org/2000/svg\" d=\"M460.1430808454916,1973.8181207577388v101.29236869017245h1344.76165330305v-101.29236869017245z\" fill=\"none\" stroke=\"#ff0000\" stroke-opacity=\"0.2\" stroke-width=\"4\"/><path xmlns=\"http://www.w3.org/2000/svg\" d=\"M460.1430808454916,1973.8181207577388v56.83647342522909h217.76279947699808v-56.83647342522909z\" fill=\"none\" stroke=\"#7aecec\" stroke-opacity=\"1.0\" stroke-width=\"2\"/><path xmlns=\"http://www.w3.org/2000/svg\" d=\"M726.2976135396004,1973.8181207577388v56.83647342522909h556.5049319967729v-56.83647342522909z\" fill=\"none\" stroke=\"#bfeeb7\" stroke-opacity=\"1.0\" stroke-width=\"2\"/><path xmlns=\"http://www.w3.org/2000/svg\" d=\"M1427.9777451877053,1973.8181207577388v56.83647342522909h48.39173321711064v-56.83647342522909z\" fill=\"none\" stroke=\"#feca74\" stroke-opacity=\"1.0\" stroke-width=\"2\"/><path xmlns=\"http://www.w3.org/2000/svg\" d=\"M1524.7612116219266,1973.8181207577388v56.83647342522909h169.37106625988736v-56.83647342522909z\" fill=\"none\" stroke=\"#bfeeb7\" stroke-opacity=\"1.0\" stroke-width=\"2\"/><path xmlns=\"http://www.w3.org/2000/svg\" d=\"M461.0953167613119,2021.1869321266809v53.92355732123042h119.98298369528835v-53.92355732123042z\" fill=\"none\" stroke=\"#7aecec\" stroke-opacity=\"1.0\" stroke-width=\"2\"/><path xmlns=\"http://www.w3.org/2000/svg\" d=\"M629.0714939347156,2021.1869321266809v53.92355732123042h431.9387413030381v-53.92355732123042z\" fill=\"none\" stroke=\"#bfeeb7\" stroke-opacity=\"1.0\" stroke-width=\"2\"/><path xmlns=\"http://www.w3.org/2000/svg\" d=\"M1204.9898156720997,2021.1869321266809v53.92355732123042h47.993193478115245v-53.92355732123042z\" fill=\"none\" stroke=\"#feca74\" stroke-opacity=\"1.0\" stroke-width=\"2\"/><path xmlns=\"http://www.w3.org/2000/svg\" d=\"M1324.9727993673882,2021.1869321266809v53.92355732123042h455.93533804209574v-53.92355732123042z\" fill=\"none\" stroke=\"#bfeeb7\" stroke-opacity=\"1.0\" stroke-width=\"2\"/></svg>"
        }
      }
    },
    {
      "id": "https://gallica.bnf.fr/iiif/ark:/12148/bpt6k62929887/p345-tag-2026",
      "type": "Annotation",
      "motivation": "tagging",
      "body": {
        "type": "TextualBody",
        "value": "Dor, rue du Bacq, n. 1091 ;\u2014de la Fontaine-de-Grenelle.\nDreux, rue du Montblanc, n.\u00b0 415,\u2014de la Place-Vend\u00f4me.\nDroz, march\u00e9 Neuf, n.\u00b0 22, \u2014de la Cit\u00e9.\nDruan, rue Denis, n.\u00b0 29, \u2014de Bon-Conseil.\nDubait, rue Martin, n.\u00b0 365,\u2014des Amis-de-la-Patrie.\n",
        "format": "text/plain",
        "language": "fr"
      },
      "target": {
        "type": "SpecificResource",
        "source": "https://gallica.bnf.fr/iiif/ark:/12148/bpt6k62929887/p345",
        "selector": {
          "type": "SvgSelector",
          "value": "<svg xmlns=\"http://www.w3.org/2000/svg\"><path xmlns=\"http://www.w3.org/2000/svg\" d=\"M461.86861167536614,2068.01767941316v240.78317892551377h1362.000185512723v-240.78317892551377z\" fill=\"none\" stroke=\"#ff0000\" stroke-opacity=\"0.2\" stroke-width=\"4\"/><path xmlns=\"http://www.w3.org/2000/svg\" d=\"M461.86861167536614,2068.01767941316v54.47631172339106h71.21357260334064v-54.47631172339106z\" fill=\"none\" stroke=\"#7aecec\" stroke-opacity=\"1.0\" stroke-width=\"2\"/><path xmlns=\"http://www.w3.org/2000/svg\" d=\"M580.5578993476006,2068.01767941316v54.47631172339106h261.1164328789157v-54.47631172339106z\" fill=\"none\" stroke=\"#bfeeb7\" stroke-opacity=\"1.0\" stroke-width=\"2\"/><path xmlns=\"http://www.w3.org/2000/svg\" d=\"M960.3636198987507,2068.01767941316v54.47631172339106h94.95143013778744v-54.47631172339106z\" fill=\"none\" stroke=\"#feca74\" stroke-opacity=\"1.0\" stroke-width=\"2\"/><path xmlns=\"http://www.w3.org/2000/svg\" d=\"M1126.5286226398787,2068.01767941316v54.47631172339106h617.184295895619v-54.47631172339106z\" fill=\"none\" stroke=\"#bfeeb7\" stroke-opacity=\"1.0\" stroke-width=\"2\"/><path xmlns=\"http://www.w3.org/2000/svg\" d=\"M462.98977546278036,2115.426453431447v54.24624637762736h126.00731682641745v-54.24624637762736z\" fill=\"none\" stroke=\"#7aecec\" stroke-opacity=\"1.0\" stroke-width=\"2\"/><path xmlns=\"http://www.w3.org/2000/svg\" d=\"M639.4000190197648,2115.426453431447v54.24624637762736h403.22341384453586v-54.24624637762736z\" fill=\"none\" stroke=\"#bfeeb7\" stroke-opacity=\"1.0\" stroke-width=\"2\"/><path xmlns=\"http://www.w3.org/2000/svg\" d=\"M1193.8322130560018,2115.426453431447v54.24624637762736h75.60439009585036v-54.24624637762736z\" fill=\"none\" stroke=\"#feca74\" stroke-opacity=\"1.0\" stroke-width=\"2\"/><path xmlns=\"http://www.w3.org/2000/svg\" d=\"M1319.8395298824191,2115.426453431447v54.24624637762736h478.8278039403864v-54.24624637762736z\" fill=\"none\" stroke=\"#bfeeb7\" stroke-opacity=\"1.0\" stroke-width=\"2\"/><path xmlns=\"http://www.w3.org/2000/svg\" d=\"M463.74738595637643,2159.754617611567v54.13669145107269h95.72686664566099v-54.13669145107269z\" fill=\"none\" stroke=\"#7aecec\" stroke-opacity=\"1.0\" stroke-width=\"2\"/><path xmlns=\"http://www.w3.org/2000/svg\" d=\"M607.337685924868,2159.754617611567v54.13669145107269h263.2488832755678v-54.13669145107269z\" fill=\"none\" stroke=\"#bfeeb7\" stroke-opacity=\"1.0\" stroke-width=\"2\"/><path xmlns=\"http://www.w3.org/2000/svg\" d=\"M1014.1768691689272,2159.754617611567v54.13669145107269h47.86343332283059v-54.13669145107269z\" fill=\"none\" stroke=\"#feca74\" stroke-opacity=\"1.0\" stroke-width=\"2\"/><path xmlns=\"http://www.w3.org/2000/svg\" d=\"M1133.8354524760034,2159.754617611567v54.13669145107269h239.31716661415248v-54.13669145107269z\" fill=\"none\" stroke=\"#bfeeb7\" stroke-opacity=\"1.0\" stroke-width=\"2\"/><path xmlns=\"http://www.w3.org/2000/svg\" d=\"M464.72064452892715,2207.24792321523v57.130528807640076h124.02348834783434v-57.130528807640076z\" fill=\"none\" stroke=\"#7aecec\" stroke-opacity=\"1.0\" stroke-width=\"2\"/><path xmlns=\"http://www.w3.org/2000/svg\" d=\"M638.3535282158953,2207.24792321523v57.130528807640076h223.24227902610184v-57.130528807640076z\" fill=\"none\" stroke=\"#bfeeb7\" stroke-opacity=\"1.0\" stroke-width=\"2\"/><path xmlns=\"http://www.w3.org/2000/svg\" d=\"M1010.4239932593982,2207.24792321523v57.130528807640076h49.6093953391337v-57.130528807640076z\" fill=\"none\" stroke=\"#feca74\" stroke-opacity=\"1.0\" stroke-width=\"2\"/><path xmlns=\"http://www.w3.org/2000/svg\" d=\"M1134.4474816072327,2207.24792321523v57.130528807640076h347.2657673739361v-57.130528807640076z\" fill=\"none\" stroke=\"#bfeeb7\" stroke-opacity=\"1.0\" stroke-width=\"2\"/><path xmlns=\"http://www.w3.org/2000/svg\" d=\"M465.6832335018253,2254.2059036095934v54.5949547290802h146.63764776194847v-54.5949547290802z\" fill=\"none\" stroke=\"#7aecec\" stroke-opacity=\"1.0\" stroke-width=\"2\"/><path xmlns=\"http://www.w3.org/2000/svg\" d=\"M661.2000971844233,2254.2059036095934v54.5949547290802h244.39607960324747v-54.5949547290802z\" fill=\"none\" stroke=\"#bfeeb7\" stroke-opacity=\"1.0\" stroke-width=\"2\"/><path xmlns=\"http://www.w3.org/2000/svg\" d=\"M1052.2338245496192,2254.2059036095934v54.5949547290802h73.31882388097415v-54.5949547290802z\" fill=\"none\" stroke=\"#feca74\" stroke-opacity=\"1.0\" stroke-width=\"2\"/><path xmlns=\"http://www.w3.org/2000/svg\" d=\"M1174.431864351243,2254.2059036095934v54.5949547290802h513.2317671668196v-54.5949547290802z\" fill=\"none\" stroke=\"#bfeeb7\" stroke-opacity=\"1.0\" stroke-width=\"2\"/></svg>"
        }
      }
    },
    {
      "id": "https://gallica.bnf.fr/iiif/ark:/12148/bpt6k62929887/p345-tag-2027",
      "type": "Annotation",
      "motivation": "tagging",
      "body": {
        "type": "TextualBody",
        "value": "Dubois, rue Claude, n.\u00b0 356, \u2014de l'Indivisibilit\u00e9.\nDubois, rue de la Tour, n.\u00b0 3, \u2014du Temple.\n",
        "format": "text/plain",
        "language": "fr"
      },
      "target": {
        "type": "SpecificResource",
        "source": "https://gallica.bnf.fr/iiif/ark:/12148/bpt6k62929887/p345",
        "selector": {
          "type": "SvgSelector",
          "value": "<svg xmlns=\"http://www.w3.org/2000/svg\"><path xmlns=\"http://www.w3.org/2000/svg\" d=\"M466.6489376232083,2301.3440271615987v104.96370367209101h1127.438137472237v-104.96370367209101z\" fill=\"none\" stroke=\"#ff0000\" stroke-opacity=\"0.2\" stroke-width=\"4\"/><path xmlns=\"http://www.w3.org/2000/svg\" d=\"M466.6489376232083,2301.3440271615987v54.727043112118736h135.29257649666843v-54.727043112118736z\" fill=\"none\" stroke=\"#7aecec\" stroke-opacity=\"1.0\" stroke-width=\"2\"/><path xmlns=\"http://www.w3.org/2000/svg\" d=\"M647.0390396187663,2301.3440271615987v54.727043112118736h225.4876274944474v-54.727043112118736z\" fill=\"none\" stroke=\"#bfeeb7\" stroke-opacity=\"1.0\" stroke-width=\"2\"/><path xmlns=\"http://www.w3.org/2000/svg\" d=\"M1007.819243609882,2301.3440271615987v54.727043112118736h67.64628824833426v-54.727043112118736z\" fill=\"none\" stroke=\"#feca74\" stroke-opacity=\"1.0\" stroke-width=\"2\"/><path xmlns=\"http://www.w3.org/2000/svg\" d=\"M1143.1118201065506,2301.3440271615987v54.727043112118736h428.4264922394501v-54.727043112118736z\" fill=\"none\" stroke=\"#bfeeb7\" stroke-opacity=\"1.0\" stroke-width=\"2\"/><path xmlns=\"http://www.w3.org/2000/svg\" d=\"M466.6489376232083,2301.3440271615987v54.727043112118736h135.29257649666843v-54.727043112118736z\" fill=\"none\" stroke=\"#7aecec\" stroke-opacity=\"1.0\" stroke-width=\"2\"/><path xmlns=\"http://www.w3.org/2000/svg\" d=\"M664.0018144138356,2348.0277467568717v58.27998407681798h343.58826235717186v-58.27998407681798z\" fill=\"none\" stroke=\"#bfeeb7\" stroke-opacity=\"1.0\" stroke-width=\"2\"/><path xmlns=\"http://www.w3.org/2000/svg\" d=\"M1154.8421892097954,2348.0277467568717v58.27998407681798h24.54201873979798v-58.27998407681798z\" fill=\"none\" stroke=\"#feca74\" stroke-opacity=\"1.0\" stroke-width=\"2\"/><path xmlns=\"http://www.w3.org/2000/svg\" d=\"M1253.0102641689873,2348.0277467568717v58.27998407681798h220.87816865818195v-58.27998407681798z\" fill=\"none\" stroke=\"#bfeeb7\" stroke-opacity=\"1.0\" stroke-width=\"2\"/></svg>"
        }
      }
    },
    {
      "id": "https://gallica.bnf.fr/iiif/ark:/12148/bpt6k62929887/p345-tag-2028",
      "type": "Annotation",
      "motivation": "tagging",
      "body": {
        "type": "TextualBody",
        "value": "Duchesne, rue du Cherche-Midy, n.\u00b0 789, \u2014du Luxembourg.\n",
        "format": "text/plain",
        "language": "fr"
      },
      "target": {
        "type": "SpecificResource",
        "source": "https://gallica.bnf.fr/iiif/ark:/12148/bpt6k62929887/p345",
        "selector": {
          "type": "SvgSelector",
          "value": "<svg xmlns=\"http://www.w3.org/2000/svg\"><path xmlns=\"http://www.w3.org/2000/svg\" d=\"M468.6385923783461,2396.4258764584856v54.094985882441506h1360.6903754120183v-54.094985882441506z\" fill=\"none\" stroke=\"#ff0000\" stroke-opacity=\"0.2\" stroke-width=\"4\"/><path xmlns=\"http://www.w3.org/2000/svg\" d=\"M468.6385923783461,2396.4258764584856v54.094985882441506h197.91860005992993v-54.094985882441506z\" fill=\"none\" stroke=\"#7aecec\" stroke-opacity=\"1.0\" stroke-width=\"2\"/><path xmlns=\"http://www.w3.org/2000/svg\" d=\"M716.0368424532585,2396.4258764584856v54.094985882441506h470.05667514233346v-54.094985882441506z\" fill=\"none\" stroke=\"#bfeeb7\" stroke-opacity=\"1.0\" stroke-width=\"2\"/><path xmlns=\"http://www.w3.org/2000/svg\" d=\"M1334.5324676405396,2396.4258764584856v54.094985882441506h74.21947502247372v-54.094985882441506z\" fill=\"none\" stroke=\"#feca74\" stroke-opacity=\"1.0\" stroke-width=\"2\"/><path xmlns=\"http://www.w3.org/2000/svg\" d=\"M1482.971417685487,2396.4258764584856v54.094985882441506h321.61772509738614v-54.094985882441506z\" fill=\"none\" stroke=\"#bfeeb7\" stroke-opacity=\"1.0\" stroke-width=\"2\"/></svg>"
        }
      }
    },
    {
      "id": "https://gallica.bnf.fr/iiif/ark:/12148/bpt6k62929887/p345-tag-2029",
      "type": "Annotation",
      "motivation": "tagging",
      "body": {
        "type": "TextualBody",
        "value": "Duclot, rue dufaubourg Antoine, n.\u00b0 219,\u2014des Quinze-Vingts.\n",
        "format": "text/plain",
        "language": "fr"
      },
      "target": {
        "type": "SpecificResource",
        "source": "https://gallica.bnf.fr/iiif/ark:/12148/bpt6k62929887/p345",
        "selector": {
          "type": "SvgSelector",
          "value": "<svg xmlns=\"http://www.w3.org/2000/svg\"><path xmlns=\"http://www.w3.org/2000/svg\" d=\"M469.5750915877124,2443.0118680795026v57.97746308644673h1360.7356994111847v-57.97746308644673z\" fill=\"none\" stroke=\"#ff0000\" stroke-opacity=\"0.2\" stroke-width=\"4\"/><path xmlns=\"http://www.w3.org/2000/svg\" d=\"M469.5750915877124,2443.0118680795026v57.97746308644673h138.37990163503574v-57.97746308644673z\" fill=\"none\" stroke=\"#7aecec\" stroke-opacity=\"1.0\" stroke-width=\"2\"/><path xmlns=\"http://www.w3.org/2000/svg\" d=\"M654.0816271010933,2443.0118680795026v57.97746308644673h507.39297266179767v-57.97746308644673z\" fill=\"none\" stroke=\"#bfeeb7\" stroke-opacity=\"1.0\" stroke-width=\"2\"/><path xmlns=\"http://www.w3.org/2000/svg\" d=\"M1299.854501397927,2443.0118680795026v57.97746308644673h69.1899508175178v-57.97746308644673z\" fill=\"none\" stroke=\"#feca74\" stroke-opacity=\"1.0\" stroke-width=\"2\"/><path xmlns=\"http://www.w3.org/2000/svg\" d=\"M1415.1710860937899,2443.0118680795026v57.97746308644673h392.0763879659345v-57.97746308644673z\" fill=\"none\" stroke=\"#bfeeb7\" stroke-opacity=\"1.0\" stroke-width=\"2\"/></svg>"
        }
      }
    },
    {
      "id": "https://gallica.bnf.fr/iiif/ark:/12148/bpt6k62929887/p345-tag-2030",
      "type": "Annotation",
      "motivation": "tagging",
      "body": {
        "type": "TextualBody",
        "value": "Ducrot, rue des Tournelles, n.\u00b0 46, - de l'Indivisibilit\u00e9.\n( 323\n",
        "format": "text/plain",
        "language": "fr"
      },
      "target": {
        "type": "SpecificResource",
        "source": "https://gallica.bnf.fr/iiif/ark:/12148/bpt6k62929887/p345",
        "selector": {
          "type": "SvgSelector",
          "value": "<svg xmlns=\"http://www.w3.org/2000/svg\"><path xmlns=\"http://www.w3.org/2000/svg\" d=\"M427.05214324257116,290.48370895410574v2251.769983275483h1291.9761860732365v-2251.769983275483z\" fill=\"none\" stroke=\"#ff0000\" stroke-opacity=\"0.2\" stroke-width=\"4\"/><path xmlns=\"http://www.w3.org/2000/svg\" d=\"M470.4830054502089,2488.175886551539v54.07780567804957h129.15986108954468v-54.07780567804957z\" fill=\"none\" stroke=\"#7aecec\" stroke-opacity=\"1.0\" stroke-width=\"2\"/><path xmlns=\"http://www.w3.org/2000/svg\" d=\"M642.6961535696018,2488.175886551539v54.07780567804957h387.4795832686341v-54.07780567804957z\" fill=\"none\" stroke=\"#bfeeb7\" stroke-opacity=\"1.0\" stroke-width=\"2\"/><path xmlns=\"http://www.w3.org/2000/svg\" d=\"M1159.3355979277806,2488.175886551539v54.07780567804957h43.05328702984821v-54.07780567804957z\" fill=\"none\" stroke=\"#feca74\" stroke-opacity=\"1.0\" stroke-width=\"2\"/><path xmlns=\"http://www.w3.org/2000/svg\" d=\"M1288.4954590173252,2488.175886551539v54.07780567804957h409.0062267835581v-54.07780567804957z\" fill=\"none\" stroke=\"#bfeeb7\" stroke-opacity=\"1.0\" stroke-width=\"2\"/></svg>"
        }
      }
    }
  ]
}